odoo/addons/account_cash_discount_reconcile_write_off/README.rst
odoo/addons/account_cash_discount_reconcile_write_off/__init__.py
odoo/addons/account_cash_discount_reconcile_write_off/__manifest__.py
odoo/addons/account_cash_discount_reconcile_write_off/i18n/account_cash_discount_reconcile_write_off.pot
odoo/addons/account_cash_discount_reconcile_write_off/i18n/es.po
odoo/addons/account_cash_discount_reconcile_write_off/i18n/it.po
odoo/addons/account_cash_discount_reconcile_write_off/models/__init__.py
odoo/addons/account_cash_discount_reconcile_write_off/models/account_reconciliation.py
odoo/addons/account_cash_discount_reconcile_write_off/readme/CONTRIBUTORS.rst
odoo/addons/account_cash_discount_reconcile_write_off/readme/DESCRIPTION.rst
odoo/addons/account_cash_discount_reconcile_write_off/readme/USAGE.rst
odoo/addons/account_cash_discount_reconcile_write_off/static/description/icon.png
odoo/addons/account_cash_discount_reconcile_write_off/static/description/index.html
odoo/addons/account_cash_discount_reconcile_write_off/static/src/xml/reconcile_info_popover.xml
odoo/addons/account_cash_discount_reconcile_write_off/tests/__init__.py
odoo/addons/account_cash_discount_reconcile_write_off/tests/test_account_reconcile_prepare_move.py
odoo14_addon_account_cash_discount_reconcile_write_off-14.0.1.0.1.dev6.dist-info/METADATA
odoo14_addon_account_cash_discount_reconcile_write_off-14.0.1.0.1.dev6.dist-info/WHEEL
odoo14_addon_account_cash_discount_reconcile_write_off-14.0.1.0.1.dev6.dist-info/top_level.txt
odoo14_addon_account_cash_discount_reconcile_write_off-14.0.1.0.1.dev6.dist-info/RECORD
